mayatest/__init__.py
mayatest/__main__.py
mayatest/cli.py
mayatest/mayaloc.py
mayatest/runner.py
mayatest-0.1.2.dist-info/top_level.txt
mayatest-0.1.2.dist-info/entry_points.txt
mayatest-0.1.2.dist-info/METADATA
mayatest-0.1.2.dist-info/DESCRIPTION.rst
mayatest-0.1.2.dist-info/metadata.json
mayatest-0.1.2.dist-info/WHEEL
mayatest-0.1.2.dist-info/RECORD
