Metadata-Version: 2.0
Name: mayatest
Version: 0.1.2
Summary: Test Autodesk Maya scripts and modules with pytest
Home-page: https://github.com/arubertoson/mayatest
Author: Marcus Albertsson
Author-email: marcus.arubertoson@gmail.com
License: MIT
Platform: UNKNOWN
Classifier: Development Status :: 3 - Alpha
Classifier: Programming Language :: Python :: 2.7
Classifier: Intended Audience :: End Users/Desktop
Classifier: Environment :: Console
Requires-Dist: pytest
Requires-Dist: mock
